.zenodo.json
AUTHORS.rst
CITATION
CONTRIBUTING.rst
HISTORY.rst
LICENSE
Makefile
README.rst
pyproject.toml
tox.ini
arosics/CoReg.py
arosics/CoReg_local.py
arosics/DeShifter.py
arosics/Tie_Point_Grid.py
arosics/__init__.py
arosics/arosics_cli.py
arosics/geometry.py
arosics/plotting.py
arosics/version.py
arosics.egg-info/PKG-INFO
arosics.egg-info/SOURCES.txt
arosics.egg-info/dependency_links.txt
arosics.egg-info/entry_points.txt
arosics.egg-info/not-zip-safe
arosics.egg-info/requires.txt
arosics.egg-info/top_level.txt