Metadata-Version: 2.4
Name: arosics
Version: 1.13.0
Summary: An Automated and Robust Open-Source Image Co-Registration Software for Multi-Sensor Satellite Data
Author-email: Daniel Scheffler <daniel.scheffler@gfz.de>
License-Expression: Apache-2.0
Project-URL: Source code, https://git.gfz-potsdam.de/danschef/arosics
Project-URL: Issue Tracker, https://git.gfz-potsdam.de/danschef/arosics/-/issues
Project-URL: Documentation, https://danschef.git-pages.gfz-potsdam.de/arosics/doc/
Project-URL: Change log, https://git.gfz-potsdam.de/danschef/arosics/-/blob/main/HISTORY.rst
Project-URL: Algorithm paper, https://www.mdpi.com/2072-4292/9/7/676
Project-URL: Zenodo, https://zenodo.org/record/5093940
Keywords: arosics,image co-registration,geometric pre-processing,remote sensing,sensor fusion
Classifier: Development Status :: 5 - Production/Stable
Classifier: Intended Audience :: Science/Research
Classifier: Topic :: Scientific/Engineering
Classifier: Natural Language :: English
Classifier: Programming Language :: Python :: 3
Classifier: Programming Language :: Python :: 3.8
Classifier: Programming Language :: Python :: 3.9
Classifier: Programming Language :: Python :: 3.10
Classifier: Programming Language :: Python :: 3.11
Classifier: Programming Language :: Python :: 3.12
Requires-Python: >=3.8
License-File: LICENSE
License-File: AUTHORS.rst
Requires-Dist: cartopy
Requires-Dist: cmocean
Requires-Dist: folium!=0.12.0,>=0.6.0
Requires-Dist: gdal
Requires-Dist: geoarray>=0.15.0
Requires-Dist: geojson
Requires-Dist: geopandas
Requires-Dist: joblib>=1.3.0
Requires-Dist: matplotlib
Requires-Dist: numpy
Requires-Dist: pandas
Requires-Dist: plotly
Requires-Dist: pyproj>2.2.0
Requires-Dist: py_tools_ds>=0.23.2
Requires-Dist: scikit-image>=0.21.0
Requires-Dist: scipy>=1.7.0
Requires-Dist: shapely
Provides-Extra: interactive-plotting
Requires-Dist: holoviews>1.12.7; extra == "interactive-plotting"
Requires-Dist: ipython; extra == "interactive-plotting"
Requires-Dist: nbformat; extra == "interactive-plotting"
Provides-Extra: interpolation
Requires-Dist: pykrige; extra == "interpolation"
Requires-Dist: scikit-learn; extra == "interpolation"
Provides-Extra: doc
Requires-Dist: sphinx-argparse; extra == "doc"
Requires-Dist: sphinx_rtd_theme; extra == "doc"
Requires-Dist: sphinx-autodoc-typehints; extra == "doc"
Provides-Extra: test
Requires-Dist: pytest; extra == "test"
Requires-Dist: pytest-cov; extra == "test"
Requires-Dist: pytest-reporter-html1<0.9.4; extra == "test"
Requires-Dist: urlchecker; extra == "test"
Requires-Dist: arosics[interactive_plotting]; extra == "test"
Requires-Dist: arosics[interpolation]; extra == "test"
Provides-Extra: lint
Requires-Dist: flake8; extra == "lint"
Requires-Dist: pycodestyle; extra == "lint"
Requires-Dist: pydocstyle; extra == "lint"
Provides-Extra: dev
Requires-Dist: arosics[test]; extra == "dev"
Requires-Dist: arosics[doc]; extra == "dev"
Requires-Dist: arosics[lint]; extra == "dev"
Dynamic: license-file
